lms_synergy_library/__init__.py
lms_synergy_library/constants.py
lms_synergy_library/exceptions.py
lms_synergy_library/lms_synergy_library.py
lms_synergy_library/utils.py
lms_synergy_library-0.2.2.dist-info/LICENSE
lms_synergy_library-0.2.2.dist-info/METADATA
lms_synergy_library-0.2.2.dist-info/WHEEL
lms_synergy_library-0.2.2.dist-info/top_level.txt
lms_synergy_library-0.2.2.dist-info/RECORD
