Metadata-Version: 2.1
Name: lms-synergy-library
Version: 0.2.2
Summary: A library that allows you to work with LMS
Author-email: Nikita Kovinjko <kotorkovsciy@gmail.com>
Project-URL: Homepage, https://github.com/kotorkovsciy/lms-synergy-library
Project-URL: Bug Tracker, https://github.com/kotorkovsciy/lms-synergy-library/issues
Classifier: Programming Language :: Python :: 3.8
Classifier: Programming Language :: Python :: 3.9
Classifier: License :: OSI Approved :: MIT License
Classifier: Operating System :: OS Independent
Requires-Python: >=3.8
License-File: LICENSE
Requires-Dist: requests
Requires-Dist: beautifulsoup4
Requires-Dist: fake-useragent
